pypdfe/EstimatePDFmv.py
pypdfe/__init__.py
pypdfe/PDF-Estimator/ChebyShev.cpp
pypdfe/PDF-Estimator/ChebyShev.h
pypdfe/PDF-Estimator/InputData.cpp
pypdfe/PDF-Estimator/InputData.h
pypdfe/PDF-Estimator/InputParameters.cpp
pypdfe/PDF-Estimator/InputParameters.h
pypdfe/PDF-Estimator/JointProbability.cpp
pypdfe/PDF-Estimator/JointProbability.h
pypdfe/PDF-Estimator/MinimizeScore.cpp
pypdfe/PDF-Estimator/MinimizeScore.h
pypdfe/PDF-Estimator/OutputControl.cpp
pypdfe/PDF-Estimator/OutputControl.h
pypdfe/PDF-Estimator/Score.cpp
pypdfe/PDF-Estimator/Score.h
pypdfe/PDF-Estimator/ScoreQZ.cpp
pypdfe/PDF-Estimator/ScoreQZ.h
pypdfe/PDF-Estimator/Variable.cpp
pypdfe/PDF-Estimator/Variable.h
pypdfe/PDF-Estimator/WriteResults.cpp
pypdfe/PDF-Estimator/WriteResults.h
pypdfe/PDF-Estimator/callPDF.cpp
pypdfe/PDF-Estimator/callPDF.h
pypdfe/PDF-Estimator/mvPDFMain.cpp
test4957-0.2.2.dist-info/METADATA
test4957-0.2.2.dist-info/WHEEL
test4957-0.2.2.dist-info/top_level.txt
test4957-0.2.2.dist-info/RECORD
